tacotron_cleaner/__init__.py
tacotron_cleaner/cleaners.py
tacotron_cleaner/cmudict.py
tacotron_cleaner/numbers.py
tacotron_cleaner/symbols.py
vietnamese_cleaner/__init__.py
vietnamese_cleaner/regex_tokenize.py
vietnamese_cleaner/vietnameseNormUniStd.py
vietnamese_cleaner/vietnamese_cleaners.py
espnet_tts_frontend-0.0.3.dist-info/METADATA
espnet_tts_frontend-0.0.3.dist-info/WHEEL
espnet_tts_frontend-0.0.3.dist-info/top_level.txt
espnet_tts_frontend-0.0.3.dist-info/RECORD
