Metadata-Version: 2.1
Name: espnet-tts-frontend
Version: 0.0.3
Summary: UNKNOWN
Home-page: http://github.com/espnet/espnet_tts_frontend
License: UNKNOWN
Platform: UNKNOWN
Classifier: Programming Language :: Python
Classifier: Programming Language :: Python :: 3
Classifier: Programming Language :: Python :: 3.6
Classifier: Programming Language :: Python :: 3.7
Classifier: Programming Language :: Python :: 3.8
Classifier: Development Status :: 5 - Production/Stable
Classifier: Intended Audience :: Science/Research
Classifier: Operating System :: POSIX :: Linux
Classifier: License :: OSI Approved :: Apache Software License
Classifier: Topic :: Software Development :: Libraries :: Python Modules
Requires-Dist: unidecode (>=1.0.22)
Requires-Dist: inflect (>=1.0.0)
Requires-Dist: jaconv
Requires-Dist: g2p-en
Requires-Dist: pypinyin
Provides-Extra: doc
Provides-Extra: test
